handlr/__init__.py
handlr/formatter.py
test_unit/__init__.py
test_unit/test___init__.py
test_unit/test_formatter.py
handlr-0.1.0.dist-info/LICENCE
handlr-0.1.0.dist-info/METADATA
handlr-0.1.0.dist-info/WHEEL
handlr-0.1.0.dist-info/top_level.txt
handlr-0.1.0.dist-info/RECORD
