Metadata-Version: 2.1
Name: handlr
Version: 0.1.0
Summary: Python handler to logging services
Home-page: https://bitbucket.org/joetilsed/handlr/
Author: Joe Tilsed
Author-email: Joe@Tilsed.com
Keywords: python logging handler logstash elk open-source
Classifier: Programming Language :: Python :: 3.10
Classifier: Natural Language :: English
Classifier: Intended Audience :: Developers
Classifier: License :: OSI Approved :: MIT License
Classifier: Operating System :: OS Independent
License-File: LICENCE
